{
    "responses": [
        {
            "request": {
                "method": "POST",
                "path": "/api/v1/orders"
            },
            "response": {
                "status": 201,
                "body": {
                    "orderId": "ord-7891",
                    "status": "PENDING",
                    "items": [
                        { "productId": "prod-01", "quantity": 2, "unitPrice": 29.99 }
                    ],
                    "subtotal": 59.98,
                    "discount": 12.00,
                    "total": 47.98,
                    "coupon": "SAVE20",
                    "createdAt": "2024-06-27T15:05:00Z"
                }
            }
        }
    ]
}
